amazonproductreviews.py
amazonproductreviews-0.1.3.dist-info/METADATA
amazonproductreviews-0.1.3.dist-info/WHEEL
amazonproductreviews-0.1.3.dist-info/RECORD
